odoo/addons/stock_force_assign_by_type/README.rst
odoo/addons/stock_force_assign_by_type/__init__.py
odoo/addons/stock_force_assign_by_type/__manifest__.py
odoo/addons/stock_force_assign_by_type/i18n/es.po
odoo/addons/stock_force_assign_by_type/i18n/stock_force_assign_by_type.pot
odoo/addons/stock_force_assign_by_type/models/__init__.py
odoo/addons/stock_force_assign_by_type/models/stock_move.py
odoo/addons/stock_force_assign_by_type/models/stock_picking.py
odoo/addons/stock_force_assign_by_type/models/stock_picking_type.py
odoo/addons/stock_force_assign_by_type/readme/CONFIGURE.rst
odoo/addons/stock_force_assign_by_type/readme/CONTEXT.rst
odoo/addons/stock_force_assign_by_type/readme/CONTRIBUTORS.rst
odoo/addons/stock_force_assign_by_type/readme/DESCRIPTION.rst
odoo/addons/stock_force_assign_by_type/readme/USAGE.rst
odoo/addons/stock_force_assign_by_type/static/description/icon.png
odoo/addons/stock_force_assign_by_type/static/description/index.html
odoo/addons/stock_force_assign_by_type/tests/__init__.py
odoo/addons/stock_force_assign_by_type/tests/test_stock_force_assign_by_type.py
odoo/addons/stock_force_assign_by_type/views/stock_picking_views.xml
odoo_addon_stock_force_assign_by_type-15.0.1.0.1.dist-info/METADATA
odoo_addon_stock_force_assign_by_type-15.0.1.0.1.dist-info/WHEEL
odoo_addon_stock_force_assign_by_type-15.0.1.0.1.dist-info/top_level.txt
odoo_addon_stock_force_assign_by_type-15.0.1.0.1.dist-info/RECORD
